dataproc_custom_trigger/__init__.py
dataproc_custom_trigger/triggers.py
dataproc_custom_trigger-0.1.7.dist-info/METADATA
dataproc_custom_trigger-0.1.7.dist-info/WHEEL
dataproc_custom_trigger-0.1.7.dist-info/top_level.txt
dataproc_custom_trigger-0.1.7.dist-info/RECORD
