Metadata-Version: 2.2
Name: dataproc_custom_trigger
Version: 0.1.7
Requires-Dist: apache-airflow>=2.2
Requires-Dist: apache-airflow-providers-google>=6.0.0
Dynamic: requires-dist
